vcspack6/__init__.py
vcspack6/utils.py
vcspack6-0.2.dist-info/LICENSE.txt
vcspack6-0.2.dist-info/METADATA
vcspack6-0.2.dist-info/WHEEL
vcspack6-0.2.dist-info/top_level.txt
vcspack6-0.2.dist-info/RECORD
