Metadata-Version: 2.1
Name: vcspack6
Version: 0.2
Summary: vcspack utilities
Home-page: UNKNOWN
Author: vinay
Author-email: vinaygn@gmail.com
License: MIT
Keywords: PYTHON,UTILITIES
Platform: UNKNOWN
